movie_poster_widget/__init__.py
movie_poster_widget/widget.py
movie_poster_widget-0.1.0.dist-info/LICENSE
movie_poster_widget-0.1.0.dist-info/METADATA
movie_poster_widget-0.1.0.dist-info/WHEEL
movie_poster_widget-0.1.0.dist-info/top_level.txt
movie_poster_widget-0.1.0.dist-info/RECORD
