Metadata-Version: 2.1
Name: movie_poster_widget
Version: 0.1.0
Summary: A widget for displaying movie posters
Home-page: https://github.com/votre_nom/movie_poster_widget
Author: Votre Nom
Author-email: votre.email@example.com
Classifier: Programming Language :: Python :: 3
Classifier: License :: OSI Approved :: MIT License
Classifier: Operating System :: OS Independent
Requires-Python: >=3.6
License-File: LICENSE
Requires-Dist: PySide6
